collective.redirectacquired-2.0a1-py3.11-nspkg.pth
collective/redirectacquired/__init__.py
collective/redirectacquired/configure.zcml
collective/redirectacquired/interfaces.py
collective/redirectacquired/testing.py
collective/redirectacquired/testing.zcml
collective/redirectacquired/traverse.py
collective/redirectacquired/tests/__init__.py
collective/redirectacquired/tests/test_acquisition.py
collective/redirectacquired/tests/resources/my_view.pt
collective/redirectacquired/tests/resources/sunset.png
collective.redirectacquired-2.0a1.dist-info/METADATA
collective.redirectacquired-2.0a1.dist-info/WHEEL
collective.redirectacquired-2.0a1.dist-info/entry_points.txt
collective.redirectacquired-2.0a1.dist-info/namespace_packages.txt
collective.redirectacquired-2.0a1.dist-info/top_level.txt
collective.redirectacquired-2.0a1.dist-info/RECORD
