Metadata-Version: 2.1
Name: collective.redirectacquired
Version: 2.0a1
Summary: Redirect when traversing to acquired content outside the current path.
Home-page: https://github.com/collective/collective.redirectacquired
Author: Godefroid Chapelle
Author-email: gotcha@bubblenet.be
License: GPL
Keywords: traversal acquisition
Classifier: Framework :: Plone
Classifier: Framework :: Plone :: 6.0
Classifier: Programming Language :: Python
Classifier: Programming Language :: Python :: 3.8
Classifier: Programming Language :: Python :: 3.9
Classifier: Programming Language :: Python :: 3.10
Classifier: Programming Language :: Python :: 3.11
Classifier: License :: OSI Approved :: GNU General Public License v2 (GPLv2)
Classifier: Operating System :: OS Independent
Requires-Python: >=3.7
Requires-Dist: setuptools
Requires-Dist: Products.CMFCore
Requires-Dist: Products.CMFPlone
Requires-Dist: Zope2
Requires-Dist: zExceptions
Requires-Dist: zope.component
Requires-Dist: zope.interface
Requires-Dist: plone.app.caching
Provides-Extra: test
Requires-Dist: Products.CMFPlone[test] ; extra == 'test'
